__init__.py
cloudicorn_aws.py
cloudicorn_aws-0.10.dist-info/METADATA
cloudicorn_aws-0.10.dist-info/WHEEL
cloudicorn_aws-0.10.dist-info/top_level.txt
cloudicorn_aws-0.10.dist-info/RECORD
