Metadata-Version: 2.1
Name: cloudicorn-aws
Version: 0.10
Summary: AWS Specific extension for cloudicorn-cli
Home-page: https://github.com/jumidev/cloudicorn-cli
Author: krezreb
Author-email: josephbeeson@gmail.com
License: MIT
Requires-Dist: boto3
